{
    "annotation": "",
    "authorName": "Jed Peterson",
    "chartitem": "",
    "endrange": "",
    "excelSettingsType": "",
    "file": "https://exceng.sharepoint.com/sites/extranet/SharedFiles/General/Office%20Map%2003.2023.pdf",
    "listId": "43b37f78-ed0f-4e3a-bc51-6097ee82756e",
    "modifiedAt": "2023-05-26T16:24:18Z",
    "photoUrl": "",
    "rangeitem": "",
    "siteId": "2562384b-fed6-491c-93ab-9759f76aca6b",
    "startPage": 1,
    "startrange": "",
    "tableitem": "",
    "uniqueId": "2774e479-c2d1-4e0f-90cd-b1380ac32631",
    "wdallowinteractivity": true,
    "wdhidegridlines": true,
    "wdhideheaders": true,
    "webId": "d60b02e9-db4c-49b0-bfce-f8408fe4cf33",
    "link": "https://exceng.sharepoint.com/:b:/r/sites/extranet/SharedFiles/General/Office%20Map%2003.2023.pdf?csf=1&web=1&e=rolxoG",
    "webAbsoluteUrl": "https://exceng.sharepoint.com/sites/extranet"
  }